parsernaam/__init__.py
parsernaam/config.py
parsernaam/model.py
parsernaam/naam.py
parsernaam/parse.py
parsernaam/utils.py
parsernaam/models/parsernaam.joblib
parsernaam/models/parsernaam.pt
parsernaam/models/parsernaam_pos.pt
parsernaam/notebooks/01_data_prep.ipynb
parsernaam/notebooks/02_train.ipynb
parsernaam/notebooks/03_pos_data_prep.ipynb
parsernaam/notebooks/04_pos_train.ipynb
parsernaam/notebooks/fl_lstm.ipynb
parsernaam/notebooks/pos_name_parser.ipynb
parsernaam/tests/__init__.py
parsernaam/tests/test_010_name_parser.py
parsernaam/tests/test_020_edge_cases.py
parsernaam-0.1.1.dist-info/licenses/LICENSE
parsernaam-0.1.1.dist-info/METADATA
parsernaam-0.1.1.dist-info/WHEEL
parsernaam-0.1.1.dist-info/entry_points.txt
parsernaam-0.1.1.dist-info/top_level.txt
parsernaam-0.1.1.dist-info/RECORD
