Metadata-Version: 2.4
Name: parsernaam
Version: 0.1.1
Summary: ML-assisted name parser for Indian and international names
Author-email: Rajashekar Chintalapati <rajshekar.ch@gmail.com>, Gaurav Sood <gsood07@gmail.com>
License-Expression: MIT
Project-URL: Homepage, https://github.com/appeler/parsernaam
Project-URL: Repository, https://github.com/appeler/parsernaam
Project-URL: Bug Tracker, https://github.com/appeler/parsernaam/issues
Keywords: name-parser,names,machine-learning,nlp,indian-names,lstm,pytorch
Classifier: Development Status :: 4 - Beta
Classifier: Intended Audience :: Developers
Classifier: Programming Language :: Python :: 3.8
Classifier: Programming Language :: Python :: 3.9
Classifier: Programming Language :: Python :: 3.10
Classifier: Programming Language :: Python :: 3.11
Classifier: Programming Language :: Python :: 3.12
Classifier: Programming Language :: Python :: 3.13
Classifier: Topic :: Scientific/Engineering :: Information Analysis
Classifier: Topic :: Software Development :: Libraries :: Python Modules
Classifier: Topic :: Text Processing :: Linguistic
Classifier: Topic :: Utilities
Requires-Python: >=3.8
License-File: LICENSE
Requires-Dist: torch>=2.0.1
Requires-Dist: pandas>=1.5.0
Requires-Dist: joblib>=1.3.0
Requires-Dist: scikit-learn>=1.3.0
Requires-Dist: numpy<2.0.0,>=1.21.0
Provides-Extra: dev
Requires-Dist: check-manifest; extra == "dev"
Requires-Dist: black; extra == "dev"
Requires-Dist: flake8; extra == "dev"
Requires-Dist: isort; extra == "dev"
Provides-Extra: test
Requires-Dist: pytest>=6.0; extra == "test"
Requires-Dist: coverage; extra == "test"
Requires-Dist: tox; extra == "test"
Dynamic: license-file
